pyfunctools/__init__.py
pyfunctools/__version__.py
pyfunctools/at.py
pyfunctools/chunk.py
pyfunctools/compact.py
pyfunctools/filter.py
pyfunctools/flatten.py
pyfunctools/foreach.py
pyfunctools/map.py
pyfunctools/memoize.py
pyfunctools/pipeline.py
pyfunctools/reduce.py
pyfunctools/utils.py
pyfunctools-0.6.0.dist-info/LICENSE
pyfunctools-0.6.0.dist-info/WHEEL
pyfunctools-0.6.0.dist-info/METADATA
pyfunctools-0.6.0.dist-info/RECORD
