Metadata-Version: 2.1
Name: pyfunctools
Version: 0.6.0
Summary: pyfunctools - Functional programming toolkit
Author: Natan Santos
Author-email: natansantosapps@gmail.com
Requires-Python: >=3.8,<4.0
Classifier: Programming Language :: Python :: 3
Classifier: Programming Language :: Python :: 3.10
Classifier: Programming Language :: Python :: 3.8
Classifier: Programming Language :: Python :: 3.9
